wsctools/__init__.py
wsctools/wsheaders.py
wsctools/wslogging.py
wsctools/wstranslator.py
wsctools/wsurls.py
wsctools-1.0.1.dist-info/LICENSE
wsctools-1.0.1.dist-info/METADATA
wsctools-1.0.1.dist-info/WHEEL
wsctools-1.0.1.dist-info/top_level.txt
wsctools-1.0.1.dist-info/RECORD
