Metadata-Version: 2.1
Name: wsctools
Version: 1.0.1
Summary: A collection of helper functions for web scraping
Home-page: https://github.com/LukeRenton/wsctools
Author: Luke Renton
Classifier: Programming Language :: Python :: 3
Classifier: License :: OSI Approved :: MIT License
Classifier: Operating System :: OS Independent
License-File: LICENSE
Requires-Dist: googletrans ==4.0.0-rc1
Requires-Dist: langdetect ==1.0.9
Requires-Dist: tldextract ==5.1.1
